Kookbook.py
MANIFEST.in
MIT-LICENSE
setup.py
bin/pykwartzite
lib/Kwartzite.egg-info/PKG-INFO
lib/Kwartzite.egg-info/SOURCES.txt
lib/Kwartzite.egg-info/dependency_links.txt
lib/Kwartzite.egg-info/top_level.txt
lib/kwartzite/__init__.py
lib/kwartzite/config.py
lib/kwartzite/htmltag.py
lib/kwartzite/main.py
lib/kwartzite/template.py
lib/kwartzite/util.py
lib/kwartzite/parser/BaseParser.py
lib/kwartzite/parser/ElementTreeParser.py
lib/kwartzite/parser/TextParser.py
lib/kwartzite/parser/XmlParser.py
lib/kwartzite/parser/__init__.py
lib/kwartzite/translator/ElementTreeTranslator.py
lib/kwartzite/translator/JavaTranslator.py
lib/kwartzite/translator/PythonTranslator.py
lib/kwartzite/translator/__init__.py
test/htmltag_test.py
test/input_html.py
test/test_main.py
test/testcase_helper.py
test/parser/BaseParser_test.py
test/parser/ElementTreeParser_test.py
test/parser/TextParser_test.py
test/parser/XmlParser_test.py
test/parser/__init__.py
test/translator/JavaTranslator_test.py
test/translator/PythonTranslator_test.py
test/translator/__init__.py