Metadata-Version: 1.0
Name: Kwartzite
Version: 0.0.1
Summary: Template engine for HTML using plain old html file
Home-page: http://pypi.python.org/pypi/Kwartzite
Author: makoto kuwata
Author-email: kwa@kuwata-lab.com
License: MIT License
Download-URL: http://pypi.python.org/packages/source/K/Kwartzite/Kwartzite-0.0.1.tar.gz
Platform: any
Classifier: Development Status :: 3 - Alpha
Classifier: Environment :: Console
Classifier: Intended Audience :: Developers
Classifier: License :: OSI Approved :: MIT License
Classifier: Operating System :: OS Independent
Classifier: Programming Language :: Python
Classifier: Programming Language :: Python :: 2.5
Classifier: Programming Language :: Python :: 2.6
Classifier: Programming Language :: Python :: 2.7
Classifier: Programming Language :: Python :: 3
Classifier: Programming Language :: Python :: 3.0
Classifier: Programming Language :: Python :: 3.1
Classifier: Programming Language :: Python :: 3.2
Classifier: Topic :: Software Development :: Libraries :: Python Modules
